{
  "implementationPlan": {
    "phase1": {
      "title": "Critical Features",
      "items": [
        {"feature": "Payment Integration", "effort": "high", "dependencies": [], "sketch": "Complete Stripe webhook, add refund API"},
        {"feature": "Email Service", "effort": "low", "dependencies": [], "sketch": "Add RESEND_API_KEY to .env"},
        {"feature": "Review and Rating System", "effort": "high", "dependencies": [], "sketch": "Create review model and CRUD APIs"},
        {"feature": "Refund Flow", "effort": "medium", "dependencies": [], "sketch": "Create refund service"},
        {"feature": "Kubernetes Secrets", "effort": "medium", "dependencies": [], "sketch": "Replace placeholders in secrets.yaml"},
        {"feature": "Production Environment", "effort": "low", "dependencies": [], "sketch": "Set NODE_ENV=production"},
        {"feature": "Security Hardening", "effort": "medium", "dependencies": [], "sketch": "Add dompurify, CSP headers"},
        {"feature": "Skip Links and aria-live", "effort": "medium", "dependencies": [], "sketch": "Add skip-to-content link"},
        {"feature": "Form Field Error Association", "effort": "medium", "dependencies": [], "sketch": "Link errors with aria-describedby"},
        {"feature": "ARIA Labels", "effort": "low", "dependencies": [], "sketch": "Add labels to filter controls"}
      ]
    },
    "phase2": {
      "title": "High Priority",
      "items": [
        {"feature": "Push Notifications", "effort": "high", "dependencies": [], "sketch": "Integrate Firebase Admin SDK"},
        {"feature": "Real-Time Updates", "effort": "high", "dependencies": [], "sketch": "Add Socket.io server"},
        {"feature": "SMS Notifications", "effort": "medium", "dependencies": [], "sketch": "Create sms.service.ts"},
        {"feature": "Monitoring", "effort": "medium", "dependencies": [], "sketch": "Set up Prometheus"},
        {"feature": "Timeout Middleware", "effort": "low", "dependencies": [], "sketch": "Create timeout.middleware.ts"},
        {"feature": "Rate Limit Handling", "effort": "low", "dependencies": [], "sketch": "Add 429 handling"},
        {"feature": "Network Error Detection", "effort": "medium", "dependencies": [], "sketch": "Add handleFetchError"},
        {"feature": "Click Targets Fix", "effort": "medium", "dependencies": [], "sketch": "Fix to 44px minimum"},
        {"feature": "Focus Visible States", "effort": "low", "dependencies": [], "sketch": "Add focus-visible:ring"},
        {"feature": "Export Filters", "effort": "medium", "dependencies": [], "sketch": "Add filters to export"},
        {"feature": "Trash Count Badge", "effort": "low", "dependencies": [], "sketch": "Add trash count endpoint"},
        {"feature": "Page Navigation", "effort": "medium", "dependencies": [], "sketch": "Add page controls"}
      ]
    },
    "phase3": {
      "title": "Medium Priority",
      "items": [
        {"feature": "Auto-Save Drafts", "effort": "medium", "dependencies": [], "sketch": "Add localStorage save"},
        {"feature": "Max Limits", "effort": "low", "dependencies": [], "sketch": "Add MAX limits"},
        {"feature": "Full-Text Search", "effort": "low", "dependencies": [], "sketch": "Extend search"},
        {"feature": "Animations", "effort": "low", "dependencies": [], "sketch": "Cap stagger delay"},
        {"feature": "Rejection Reason", "effort": "low", "dependencies": [], "sketch": "Show tooltip"},
        {"feature": "Empty States", "effort": "low", "dependencies": [], "sketch": "Add NoServicesSearchEmpty"},
        {"feature": "Grid Gap", "effort": "low", "dependencies": [], "sketch": "Standardize gap-6"},
        {"feature": "Sentry", "effort": "medium", "dependencies": [], "sketch": "Install Sentry"},
        {"feature": "SEO", "effort": "low", "dependencies": [], "sketch": "Add robots.txt"},
        {"feature": "Bundle Optimization", "effort": "medium", "dependencies": [], "sketch": "Configure chunks"},
        {"feature": "Cleanup", "effort": "low", "dependencies": [], "sketch": "Consolidate controllers"}
      ]
    },
    "phase4": {
      "title": "Future Improvements",
      "items": [
        {"feature": "Native Mobile", "effort": "high", "dependencies": [], "sketch": "Build React Native"},
        {"feature": "Kubernetes", "effort": "high", "dependencies": [], "sketch": "Migrate to K8s"},
        {"feature": "ML Platform", "effort": "high", "dependencies": [], "sketch": "Train ML models"},
        {"feature": "Subscriptions", "effort": "medium", "dependencies": [], "sketch": "Recurring billing"},
        {"feature": "Disputes", "effort": "medium", "dependencies": [], "sketch": "Create dispute model"},
        {"feature": "Referrals", "effort": "medium", "dependencies": [], "sketch": "Activate codes"},
        {"feature": "Packages", "effort": "medium", "dependencies": [], "sketch": "Bundle services"},
        {"feature": "Dark Mode", "effort": "medium", "dependencies": [], "sketch": "Configure dark mode"},
        {"feature": "i18n", "effort": "high", "dependencies": [], "sketch": "Add i18n framework"},
        {"feature": "PWA", "effort": "medium", "dependencies": [], "sketch": "Add service worker"},
        {"feature": "Infinite Scroll", "effort": "low", "dependencies": [], "sketch": "Replace pagination"},
        {"feature": "Commissions", "effort": "medium", "dependencies": [], "sketch": "Implement payouts"},
        {"feature": "ELK", "effort": "medium", "dependencies": [], "sketch": "Configure ELK"},
        {"feature": "Backups", "effort": "low", "dependencies": [], "sketch": "Create backup script"}
      ]
    }
  },
  "quickWins": ["Add RESEND_API_KEY", "Configure Stripe webhook", "Add skip links", "Fix aria-describedby", "Add aria-live regions", "Fix 44px click targets", "Add focus-visible", "Set MAX limits", "Add trash badge", "Configure ALLOWED_ORIGINS", "Delete duplicate controllers", "Add page nav", "Add reject tooltip", "Standardize gap-6", "Configure 429 handling"],
  "totalFeatures": 49,
  "estimatedPhases": 4
}
